[
  {
    "direction": "Flat", 
    "trend": 4, 
    "dateString": "2016-02-14T12:24:45.000Z", 
    "sgv": 129, 
    "device": "share2", 
    "date": 1455452685000, 
    "_id": "56c0724437663704c8471ad5", 
    "type": "sgv"
  }, 
  {
    "direction": "Flat", 
    "trend": 4, 
    "dateString": "2016-02-14T12:19:45.000Z", 
    "sgv": 128, 
    "device": "share2", 
    "date": 1455452385000, 
    "_id": "56c0711837663704c8471ac6", 
    "type": "sgv"
  }, 
  {
    "direction": "Flat", 
    "trend": 4, 
    "dateString": "2016-02-14T12:14:45.000Z", 
    "sgv": 126, 
    "device": "share2", 
    "date": 1455452085000, 
    "_id": "56c06fec37663704c8471aba", 
    "type": "sgv"
  }, 
  {
    "direction": "Flat", 
    "trend": 4, 
    "dateString": "2016-02-14T12:09:45.000Z", 
    "sgv": 123, 
    "device": "share2", 
    "date": 1455451785000, 
    "_id": "56c06ec137663704c8471aad", 
    "type": "sgv"
  }, 
  {
    "direction": "Flat", 
    "trend": 4, 
    "dateString": "2016-02-14T12:04:45.000Z", 
    "sgv": 124, 
    "device": "share2", 
    "date": 1455451485000, 
    "_id": "56c06d9437663704c8471aa1", 
    "type": "sgv"
  }, 
  {
    "direction": "Flat", 
    "trend": 4, 
    "dateString": "2016-02-14T11:59:45.000Z", 
    "sgv": 128, 
    "device": "share2", 
    "date": 1455451185000, 
    "_id": "56c06c6737663704c8471a96", 
    "type": "sgv"
  }, 
  {
    "direction": "Flat", 
    "trend": 4, 
    "dateString": "2016-02-14T11:54:45.000Z", 
    "sgv": 129, 
    "device": "share2", 
    "date": 1455450885000, 
    "_id": "56c06b3b37663704c8471a89", 
    "type": "sgv"
  }, 
  {
    "direction": "Flat", 
    "trend": 4, 
    "dateString": "2016-02-14T11:49:44.000Z", 
    "sgv": 134, 
    "device": "share2", 
    "date": 1455450584000, 
    "_id": "56c06a0f37663704c8471a7c", 
    "type": "sgv"
  }, 
  {
    "direction": "Flat", 
    "trend": 4, 
    "dateString": "2016-02-14T11:44:44.000Z", 
    "sgv": 136, 
    "device": "share2", 
    "date": 1455450284000, 
    "_id": "56c068e437663704c8471a70", 
    "type": "sgv"
  }, 
  {
    "direction": "Flat", 
    "trend": 4, 
    "dateString": "2016-02-14T11:39:44.000Z", 
    "sgv": 138, 
    "device": "share2", 
    "date": 1455449984000, 
    "_id": "56c067b737663704c8471a63", 
    "type": "sgv"
  }
]